{
  "nodes": [
    {"id": "Local Government"},
    {"id": "Police Department"},
    {"id": "Fire Department"},
    {"id": "Hospitals"},
    {"id": "Schools"},
    {"id": "Public Transport"},
    {"id": "Water Supply"},
    {"id": "Waste Management"},
    {"id": "Parks and Recreation"},
    {"id": "Road Maintenance"},
    {"id": "Public Libraries"},
    {"id": "Property Taxes"},
    {"id": "Sales Taxes"},
    {"id": "Income Taxes"},
    {"id": "Property Owners"},
    {"id": "Consumers"},
    {"id": "Businesses"},
    {"id": "Individuals"},
    {"id": "Federal Laws and Policies"},
    {"id": "State Laws and Policies"},
    {"id": "Local Laws and Policies"},
    {"id": "Municipal Code"},
    {"id": "Property Tax Clauses"},
    {"id": "Sales Tax Clauses"},
    {"id": "Other Fees Clauses"},
    {"id": "State Legislative Policy"},
    {"id": "State Funding Programs"},
    {"id": "Grants"},
    {"id": "Federal Legislative Policy"},
    {"id": "Federal Funding Programs"},
    {"id": "Federal Grants"}
  ],
  "links": [
    {"source": "Local Government", "target": "Police Department", "value": 1},
    {"source": "Local Government", "target": "Fire Department", "value": 1},
    {"source": "Local Government", "target": "Hospitals", "value": 1},
    {"source": "Local Government", "target": "Schools", "value": 1},
    {"source": "Local Government", "target": "Public Transport", "value": 1},
    {"source": "Local Government", "target": "Water Supply", "value": 1},
    {"source": "Local Government", "target": "Waste Management", "value": 1},
    {"source": "Local Government", "target": "Parks and Recreation", "value": 1},
    {"source": "Local Government", "target": "Road Maintenance", "value": 1},
    {"source": "Local Government", "target": "Public Libraries", "value": 1},
    {"source": "Property Taxes", "target": "Local Government", "value": 1},
    {"source": "Sales Taxes", "target": "Local Government", "value": 1},
    {"source": "Income Taxes", "target": "Local Government", "value": 1},
    {"source": "Property Owners", "target": "Property Taxes", "value": 1},
    {"source": "Consumers", "target": "Sales Taxes", "value": 1},
    {"source": "Businesses", "target": "Sales Taxes", "value": 1},
    {"source": "Businesses", "target": "Income Taxes", "value": 1},
    {"source": "Individuals", "target": "Income Taxes", "value": 1},
    {"source": "Property Taxes", "target": "State Laws and Policies", "value": 1},
    {"source": "Property Taxes", "target": "Local Laws and Policies", "value": 1},
    {"source": "Sales Taxes", "target": "State Laws and Policies", "value": 1},
    {"source": "Sales Taxes", "target": "Local Laws and Policies", "value": 1},
    {"source": "Income Taxes", "target": "Federal Laws and Policies", "value": 1},
    {"source": "Income Taxes", "target": "State Laws and Policies", "value": 1},
    {"source": "Municipal Code", "target": "Local Government", "value": 1},
    {"source": "Municipal Code", "target": "Property Tax Clauses", "value": 1},
    {"source": "Municipal Code", "target": "Sales Tax Clauses", "value": 1},
    {"source": "Municipal Code", "target": "Other Fees Clauses", "value": 1},
    {"source": "Property Tax Clauses", "target": "Property Taxes", "value": 1},
    {"source": "Sales Tax Clauses", "target": "Sales Taxes", "value": 1},
    {"source": "Other Fees Clauses", "target": "Local Government", "value": 1},
    {"source": "State Legislative Policy", "target": "State Laws and Policies", "value": 1},
    {"source": "State Legislative Policy", "target": "Property Tax Clauses", "value": 1},
    {"source": "State Legislative Policy", "target": "Sales Tax Clauses", "value": 1},
    {"source": "State Legislative Policy", "target": "Other Fees Clauses", "value": 1},
    {"source": "State Legislative Policy", "target": "State Funding Programs", "value": 1},
    {"source": "State Legislative Policy", "target": "Grants", "value": 1},
    {"source": "State Funding Programs", "target": "Local Government", "value": 1},
    {"source": "Grants", "target": "Local Government", "value": 1},
    {"source": "Federal Legislative Policy", "target": "Federal Laws and Policies", "value": 1},
    {"source": "Federal Legislative Policy", "target": "Federal Funding Programs", "value": 1},
    {"source": "Federal Legislative Policy", "target": "Federal Grants", "value": 1},
    {"source": "Federal Funding Programs", "target": "Local Government", "value": 1},
    {"source": "Federal Grants", "target": "Local Government", "value": 1}
  ]
}
